bdskeletor/__init__.py
bdskeletor/data/no-punch.png
bdskeletor/data/punch.png
bdskeletor/data/punch.wav
bdskeletor/data/skeletor-he-man-armor.png
bdskeletor/data/whiff.wav
bdskeletor/skeletor.py
bdskeletor-0.1.0.dist-info/METADATA
bdskeletor-0.1.0.dist-info/WHEEL
bdskeletor-0.1.0.dist-info/entry_points.txt
bdskeletor-0.1.0.dist-info/RECORD
